.gitignore
.travis.yml
LICENSE
MANIFEST.in
Makefile
README.md
olm_build.py
requirements.txt
setup.cfg
setup.py
test-requirements.txt
tox.ini
contrib/archlinux/pkgbuild/PKGBUILD
docs/.nojekyll
docs/Makefile
docs/conf.py
docs/index.html
docs/index.rst
docs/make.bat
docs/olm.rst
docs/doctrees/environment.pickle
docs/doctrees/index.doctree
docs/doctrees/olm.doctree
docs/html/.buildinfo
docs/html/.nojekyll
docs/html/genindex.html
docs/html/index.html
docs/html/objects.inv
docs/html/olm.html
docs/html/py-modindex.html
docs/html/search.html
docs/html/searchindex.js
docs/html/_modules/index.html
docs/html/_modules/olm/account.html
docs/html/_modules/olm/group_session.html
docs/html/_modules/olm/session.html
docs/html/_modules/olm/utility.html
docs/html/_sources/index.rst.txt
docs/html/_sources/olm.rst.txt
docs/html/_static/ajax-loader.gif
docs/html/_static/alabaster.css
docs/html/_static/basic.css
docs/html/_static/comment-bright.png
docs/html/_static/comment-close.png
docs/html/_static/comment.png
docs/html/_static/custom.css
docs/html/_static/doctools.js
docs/html/_static/documentation_options.js
docs/html/_static/down-pressed.png
docs/html/_static/down.png
docs/html/_static/file.png
docs/html/_static/jquery-3.2.1.js
docs/html/_static/jquery.js
docs/html/_static/minus.png
docs/html/_static/plus.png
docs/html/_static/pygments.css
docs/html/_static/searchtools.js
docs/html/_static/underscore-1.3.1.js
docs/html/_static/underscore.js
docs/html/_static/up-pressed.png
docs/html/_static/up.png
docs/html/_static/websupport.js
include/olm/olm.h
include/olm/pk.h
olm/__init__.py
olm/__version__.py
olm/_compat.py
olm/_finalize.py
olm/account.py
olm/group_session.py
olm/pk.py
olm/session.py
olm/utility.py
python_olm_dev.egg-info/PKG-INFO
python_olm_dev.egg-info/SOURCES.txt
python_olm_dev.egg-info/dependency_links.txt
python_olm_dev.egg-info/not-zip-safe
python_olm_dev.egg-info/requires.txt
python_olm_dev.egg-info/top_level.txt
tests/account_test.py
tests/group_session_test.py
tests/pk_test.py
tests/session_test.py