Metadata-Version: 1.0
Name: python-olm-dev
Version: 3.0
Summary: python CFFI bindings for the olm cryptographic ratchet library
Home-page: https://github.com/poljar/python-olm
Author: Damir Jelić
Author-email: poljar@termina.org.uk
License: Apache 2.0
Platform: UNKNOWN
